{ "compressionlevel":-1,
 "height":13,
 "infinite":false,
 "layers":[
        {
         "data":[0, 0, 0, 0, 0, 0, 0, 0, 0, 0, 0, 0, 0, 0, 0, 0, 0, 0, 0, 0, 0, 0, 0, 0, 0, 0, 0, 0, 0, 0, 0, 0, 0, 0, 0, 0, 0, 0, 0, 0, 0, 0, 0, 0, 0, 0, 0, 0, 0, 0, 0, 0, 0, 0, 0, 0, 0, 0, 0, 0, 0, 0, 0, 0, 0, 0, 0, 0, 0, 0, 0, 0, 0, 0, 0, 0, 0, 0, 0, 0, 0, 0, 0, 0, 0, 0, 0, 0, 0, 0, 0, 0, 0, 0, 0, 0, 0, 0, 0, 0, 0, 0, 0, 0, 0, 0, 0, 0, 0, 0, 0, 0, 0, 0, 0, 0, 0, 0, 0, 0, 0, 0, 0, 0, 0, 0, 0, 0, 0, 0, 0, 0, 0, 0, 0, 0, 0, 0, 0, 0, 0, 0, 0, 0, 0, 0, 0, 0, 0, 0, 0, 0, 0, 0, 0, 0, 0, 0, 0, 0, 0, 0, 0, 0, 0, 0, 0, 0, 0, 0, 0, 0, 0, 0, 0, 0, 0, 0, 0, 0, 0, 0, 0, 0, 0, 0, 0, 0, 0, 0, 0, 0, 0, 0, 0, 0, 0, 0, 0, 0, 0, 0, 0, 0, 0, 0, 0, 0],
         "height":13,
         "id":3,
         "name":"Border",
         "opacity":1,
         "type":"tilelayer",
         "visible":false,
         "width":16,
         "x":0,
         "y":0
        }, 
        {
         "data":[7, 8, 9, 18, 7, 0, 0, 0, 0, 0, 0, 0, 0, 0, 0, 9, 0, 0, 0, 18, 0, 0, 0, 0, 0, 0, 0, 0, 0, 0, 0, 19, 0, 0, 0, 18, 0, 0, 103, 0, 0, 103, 0, 0, 18, 27, 0, 29, 0, 0, 0, 18, 0, 0, 0, 0, 0, 0, 0, 103, 9, 18, 18, 18, 0, 0, 0, 18, 0, 0, 0, 0, 103, 0, 0, 0, 0, 0, 0, 9, 0, 0, 0, 18, 0, 0, 103, 0, 0, 0, 0, 103, 0, 0, 0, 0, 0, 0, 0, 18, 0, 0, 0, 0, 0, 0, 0, 0, 0, 47, 48, 0, 0, 0, 0, 18, 0, 0, 0, 0, 0, 0, 0, 0, 0, 0, 0, 0, 0, 0, 0, 18, 0, 0, 0, 0, 0, 103, 0, 0, 0, 0, 0, 0, 0, 0, 0, 18, 0, 0, 0, 103, 0, 0, 0, 0, 0, 103, 0, 0, 0, 0, 0, 0, 0, 0, 0, 0, 0, 0, 0, 0, 0, 0, 0, 0, 0, 0, 0, 0, 0, 0, 0, 0, 0, 0, 0, 0, 0, 0, 0, 29, 27, 0, 0, 0, 0, 0, 0, 0, 0, 0, 29, 18, 18, 18, 18, 18],
         "height":13,
         "id":4,
         "name":"Ground",
         "opacity":1,
         "type":"tilelayer",
         "visible":true,
         "width":16,
         "x":0,
         "y":0
        }, 
        {
         "data":[0, 0, 0, 0, 0, 3221225550, 3221225550, 3221225550, 3221225550, 3221225550, 3221225550, 3221225550, 3221225550, 3221225550, 3221225550, 0, 2684354638, 0, 1610612814, 0, 2684354638, 0, 0, 0, 0, 0, 0, 0, 0, 0, 0, 0, 2684354638, 0, 1610612814, 0, 2684354638, 0, 0, 0, 0, 0, 0, 1610612814, 0, 0, 97, 0, 2684354638, 0, 1610612814, 0, 2684354638, 0, 0, 0, 0, 0, 0, 0, 0, 0, 0, 0, 2684354638, 0, 1610612814, 0, 2684354638, 0, 0, 0, 0, 0, 0, 0, 0, 0, 0, 0, 2684354638, 0, 1610612814, 0, 2684354638, 0, 0, 0, 0, 0, 0, 0, 0, 0, 0, 1610612814, 2684354638, 0, 1610612814, 0, 2684354638, 0, 0, 0, 0, 0, 0, 0, 0, 0, 0, 1610612814, 2684354638, 0, 1610612814, 0, 2684354638, 0, 0, 0, 0, 0, 0, 0, 0, 0, 0, 1610612814, 2684354638, 0, 1610612814, 0, 2684354638, 0, 0, 0, 0, 0, 0, 0, 0, 0, 0, 1610612814, 2684354638, 0, 1610612814, 0, 2684354638, 0, 0, 0, 0, 0, 0, 0, 0, 0, 0, 1610612814, 2684354638, 0, 0, 3221225550, 0, 0, 0, 0, 0, 0, 0, 0, 0, 0, 0, 1610612814, 2684354638, 2684354634, 0, 0, 0, 0, 0, 0, 0, 0, 0, 0, 0, 0, 0, 1610612814, 0, 78, 78, 78, 78, 78, 78, 78, 78, 78, 78, 78, 78, 78, 78, 0],
         "height":13,
         "id":5,
         "name":"Spike\/Spring",
         "opacity":1,
         "type":"tilelayer",
         "visible":false,
         "width":16,
         "x":0,
         "y":0
        }, 
        {
         "data":[0, 0, 0, 0, 0, 0, 0, 0, 0, 0, 0, 0, 0, 0, 0, 0, 0, 0, 0, 0, 0, 0, 0, 0, 0, 0, 0, 0, 0, 0, 0, 0, 0, 0, 0, 0, 0, 0, 0, 0, 0, 0, 0, 0, 0, 0, 0, 0, 0, 0, 0, 0, 0, 0, 0, 0, 0, 0, 0, 0, 0, 0, 0, 0, 0, 0, 0, 0, 0, 0, 0, 0, 0, 0, 0, 0, 0, 0, 0, 0, 0, 0, 0, 0, 0, 0, 0, 0, 0, 0, 0, 0, 0, 0, 95, 0, 0, 0, 0, 0, 0, 0, 0, 0, 0, 0, 0, 0, 0, 0, 0, 0, 0, 0, 0, 0, 0, 0, 0, 0, 0, 0, 0, 0, 0, 0, 0, 0, 0, 0, 0, 0, 0, 0, 0, 0, 0, 0, 0, 0, 0, 0, 0, 0, 0, 0, 0, 0, 0, 0, 0, 0, 0, 0, 0, 0, 0, 0, 0, 0, 0, 0, 0, 0, 0, 0, 0, 0, 0, 0, 0, 0, 0, 0, 0, 0, 0, 0, 0, 0, 0, 0, 0, 0, 0, 0, 0, 0, 0, 0, 0, 0, 0, 0, 0, 0, 0, 0, 0, 0, 0, 0, 0, 0, 0, 0, 0, 0],
         "height":13,
         "id":6,
         "name":"Decoration",
         "opacity":1,
         "type":"tilelayer",
         "visible":true,
         "width":16,
         "x":0,
         "y":0
        }],
 "nextlayerid":7,
 "nextobjectid":1,
 "orientation":"orthogonal",
 "renderorder":"right-down",
 "tiledversion":"1.7.2",
 "tileheight":256,
 "tilesets":[
        {
         "columns":10,
         "firstgid":1,
         "image":"..\/..\/Tileset Images\/Crayon_256.png",
         "imageheight":2816,
         "imagewidth":2560,
         "margin":0,
         "name":"Crayon_Tileset",
         "spacing":0,
         "tilecount":110,
         "tileheight":256,
         "tiles":[
                {
                 "id":0,
                 "objectgroup":
                    {
                     "draworder":"index",
                     "id":2,
                     "name":"",
                     "objects":[
                            {
                             "height":256,
                             "id":1,
                             "name":"",
                             "rotation":0,
                             "type":"",
                             "visible":true,
                             "width":128,
                             "x":0,
                             "y":0
                            }],
                     "opacity":1,
                     "type":"objectgroup",
                     "visible":true,
                     "x":0,
                     "y":0
                    },
                 "properties":[
                        {
                         "name":"collider",
                         "type":"bool",
                         "value":true
                        }]
                }, 
                {
                 "id":1,
                 "objectgroup":
                    {
                     "draworder":"index",
                     "id":2,
                     "name":"",
                     "objects":[
                            {
                             "height":103,
                             "id":1,
                             "name":"",
                             "rotation":0,
                             "type":"",
                             "visible":true,
                             "width":256,
                             "x":0,
                             "y":0
                            }],
                     "opacity":1,
                     "type":"objectgroup",
                     "visible":true,
                     "x":0,
                     "y":0
                    },
                 "properties":[
                        {
                         "name":"collider",
                         "type":"bool",
                         "value":true
                        }]
                }, 
                {
                 "id":2,
                 "objectgroup":
                    {
                     "draworder":"index",
                     "id":2,
                     "name":"",
                     "objects":[
                            {
                             "height":256,
                             "id":3,
                             "name":"",
                             "rotation":0,
                             "type":"",
                             "visible":true,
                             "width":128,
                             "x":128,
                             "y":0
                            }],
                     "opacity":1,
                     "type":"objectgroup",
                     "visible":true,
                     "x":0,
                     "y":0
                    },
                 "properties":[
                        {
                         "name":"collider",
                         "type":"bool",
                         "value":true
                        }]
                }, 
                {
                 "id":3,
                 "objectgroup":
                    {
                     "draworder":"index",
                     "id":2,
                     "name":"",
                     "objects":[
                            {
                             "height":256,
                             "id":2,
                             "name":"",
                             "rotation":0,
                             "type":"",
                             "visible":true,
                             "width":128,
                             "x":0,
                             "y":0
                            }],
                     "opacity":1,
                     "type":"objectgroup",
                     "visible":true,
                     "x":0,
                     "y":0
                    },
                 "properties":[
                        {
                         "name":"collider",
                         "type":"bool",
                         "value":true
                        }]
                }, 
                {
                 "id":4,
                 "objectgroup":
                    {
                     "draworder":"index",
                     "id":2,
                     "name":"",
                     "objects":[
                            {
                             "height":103,
                             "id":1,
                             "name":"",
                             "rotation":0,
                             "type":"",
                             "visible":true,
                             "width":256,
                             "x":0,
                             "y":0
                            }],
                     "opacity":1,
                     "type":"objectgroup",
                     "visible":true,
                     "x":0,
                     "y":0
                    },
                 "properties":[
                        {
                         "name":"collider",
                         "type":"bool",
                         "value":true
                        }]
                }, 
                {
                 "id":5,
                 "objectgroup":
                    {
                     "draworder":"index",
                     "id":2,
                     "name":"",
                     "objects":[
                            {
                             "height":256,
                             "id":2,
                             "name":"",
                             "rotation":0,
                             "type":"",
                             "visible":true,
                             "width":128,
                             "x":128,
                             "y":0
                            }],
                     "opacity":1,
                     "type":"objectgroup",
                     "visible":true,
                     "x":0,
                     "y":0
                    },
                 "properties":[
                        {
                         "name":"collider",
                         "type":"bool",
                         "value":true
                        }]
                }, 
                {
                 "id":6,
                 "objectgroup":
                    {
                     "draworder":"index",
                     "id":2,
                     "name":"",
                     "objects":[
                            {
                             "height":256,
                             "id":2,
                             "name":"",
                             "rotation":0,
                             "type":"",
                             "visible":true,
                             "width":128,
                             "x":0,
                             "y":0
                            }],
                     "opacity":1,
                     "type":"objectgroup",
                     "visible":true,
                     "x":0,
                     "y":0
                    },
                 "properties":[
                        {
                         "name":"collider",
                         "type":"bool",
                         "value":true
                        }]
                }, 
                {
                 "id":7,
                 "objectgroup":
                    {
                     "draworder":"index",
                     "id":2,
                     "name":"",
                     "objects":[
                            {
                             "height":103,
                             "id":1,
                             "name":"",
                             "rotation":0,
                             "type":"",
                             "visible":true,
                             "width":256,
                             "x":0,
                             "y":0
                            }],
                     "opacity":1,
                     "type":"objectgroup",
                     "visible":true,
                     "x":0,
                     "y":0
                    },
                 "properties":[
                        {
                         "name":"collider",
                         "type":"bool",
                         "value":true
                        }]
                }, 
                {
                 "id":8,
                 "objectgroup":
                    {
                     "draworder":"index",
                     "id":2,
                     "name":"",
                     "objects":[
                            {
                             "height":256,
                             "id":2,
                             "name":"",
                             "rotation":0,
                             "type":"",
                             "visible":true,
                             "width":128,
                             "x":128,
                             "y":0
                            }],
                     "opacity":1,
                     "type":"objectgroup",
                     "visible":true,
                     "x":0,
                     "y":0
                    },
                 "properties":[
                        {
                         "name":"collider",
                         "type":"bool",
                         "value":true
                        }]
                }, 
                {
                 "id":10,
                 "objectgroup":
                    {
                     "draworder":"index",
                     "id":2,
                     "name":"",
                     "objects":[
                            {
                             "height":256,
                             "id":1,
                             "name":"",
                             "rotation":0,
                             "type":"",
                             "visible":true,
                             "width":86,
                             "x":0,
                             "y":0
                            }],
                     "opacity":1,
                     "type":"objectgroup",
                     "visible":true,
                     "x":0,
                     "y":0
                    },
                 "properties":[
                        {
                         "name":"collider",
                         "type":"bool",
                         "value":true
                        }]
                }, 
                {
                 "id":11,
                 "objectgroup":
                    {
                     "draworder":"index",
                     "id":2,
                     "name":"",
                     "objects":[
                            {
                             "height":256,
                             "id":1,
                             "name":"",
                             "rotation":0,
                             "type":"",
                             "visible":true,
                             "width":256,
                             "x":0,
                             "y":0
                            }],
                     "opacity":1,
                     "type":"objectgroup",
                     "visible":true,
                     "x":0,
                     "y":0
                    },
                 "properties":[
                        {
                         "name":"collider",
                         "type":"bool",
                         "value":true
                        }]
                }, 
                {
                 "id":12,
                 "objectgroup":
                    {
                     "draworder":"index",
                     "id":2,
                     "name":"",
                     "objects":[
                            {
                             "height":256,
                             "id":1,
                             "name":"",
                             "rotation":0,
                             "type":"",
                             "visible":true,
                             "width":125,
                             "x":131,
                             "y":0
                            }],
                     "opacity":1,
                     "type":"objectgroup",
                     "visible":true,
                     "x":0,
                     "y":0
                    },
                 "properties":[
                        {
                         "name":"collider",
                         "type":"bool",
                         "value":true
                        }]
                }, 
                {
                 "id":13,
                 "objectgroup":
                    {
                     "draworder":"index",
                     "id":2,
                     "name":"",
                     "objects":[
                            {
                             "height":256,
                             "id":1,
                             "name":"",
                             "rotation":0,
                             "type":"",
                             "visible":true,
                             "width":86,
                             "x":0,
                             "y":0
                            }],
                     "opacity":1,
                     "type":"objectgroup",
                     "visible":true,
                     "x":0,
                     "y":0
                    },
                 "properties":[
                        {
                         "name":"collider",
                         "type":"bool",
                         "value":true
                        }]
                }, 
                {
                 "id":14,
                 "objectgroup":
                    {
                     "draworder":"index",
                     "id":2,
                     "name":"",
                     "objects":[
                            {
                             "height":256,
                             "id":1,
                             "name":"",
                             "rotation":0,
                             "type":"",
                             "visible":true,
                             "width":256,
                             "x":0,
                             "y":0
                            }],
                     "opacity":1,
                     "type":"objectgroup",
                     "visible":true,
                     "x":0,
                     "y":0
                    },
                 "properties":[
                        {
                         "name":"collider",
                         "type":"bool",
                         "value":true
                        }]
                }, 
                {
                 "id":15,
                 "objectgroup":
                    {
                     "draworder":"index",
                     "id":2,
                     "name":"",
                     "objects":[
                            {
                             "height":256,
                             "id":1,
                             "name":"",
                             "rotation":0,
                             "type":"",
                             "visible":true,
                             "width":125,
                             "x":131,
                             "y":0
                            }],
                     "opacity":1,
                     "type":"objectgroup",
                     "visible":true,
                     "x":0,
                     "y":0
                    },
                 "properties":[
                        {
                         "name":"collider",
                         "type":"bool",
                         "value":true
                        }]
                }, 
                {
                 "id":16,
                 "objectgroup":
                    {
                     "draworder":"index",
                     "id":2,
                     "name":"",
                     "objects":[
                            {
                             "height":256,
                             "id":1,
                             "name":"",
                             "rotation":0,
                             "type":"",
                             "visible":true,
                             "width":87,
                             "x":0,
                             "y":0
                            }],
                     "opacity":1,
                     "type":"objectgroup",
                     "visible":true,
                     "x":0,
                     "y":0
                    },
                 "properties":[
                        {
                         "name":"collider",
                         "type":"bool",
                         "value":true
                        }]
                }, 
                {
                 "id":17,
                 "objectgroup":
                    {
                     "draworder":"index",
                     "id":2,
                     "name":"",
                     "objects":[
                            {
                             "height":256,
                             "id":1,
                             "name":"",
                             "rotation":0,
                             "type":"",
                             "visible":true,
                             "width":256,
                             "x":0,
                             "y":0
                            }],
                     "opacity":1,
                     "type":"objectgroup",
                     "visible":true,
                     "x":0,
                     "y":0
                    },
                 "properties":[
                        {
                         "name":"collider",
                         "type":"bool",
                         "value":true
                        }]
                }, 
                {
                 "id":18,
                 "objectgroup":
                    {
                     "draworder":"index",
                     "id":2,
                     "name":"",
                     "objects":[
                            {
                             "height":256,
                             "id":1,
                             "name":"",
                             "rotation":0,
                             "type":"",
                             "visible":true,
                             "width":126,
                             "x":130,
                             "y":0
                            }],
                     "opacity":1,
                     "type":"objectgroup",
                     "visible":true,
                     "x":0,
                     "y":0
                    },
                 "properties":[
                        {
                         "name":"collider",
                         "type":"bool",
                         "value":true
                        }]
                }, 
                {
                 "id":20,
                 "objectgroup":
                    {
                     "draworder":"index",
                     "id":2,
                     "name":"",
                     "objects":[
                            {
                             "height":256,
                             "id":1,
                             "name":"",
                             "rotation":0,
                             "type":"",
                             "visible":true,
                             "width":128,
                             "x":0,
                             "y":0
                            }],
                     "opacity":1,
                     "type":"objectgroup",
                     "visible":true,
                     "x":0,
                     "y":0
                    },
                 "properties":[
                        {
                         "name":"collider",
                         "type":"bool",
                         "value":true
                        }]
                }, 
                {
                 "id":21,
                 "objectgroup":
                    {
                     "draworder":"index",
                     "id":2,
                     "name":"",
                     "objects":[
                            {
                             "height":117,
                             "id":1,
                             "name":"",
                             "rotation":0,
                             "type":"",
                             "visible":true,
                             "width":256,
                             "x":0,
                             "y":139
                            }],
                     "opacity":1,
                     "type":"objectgroup",
                     "visible":true,
                     "x":0,
                     "y":0
                    },
                 "properties":[
                        {
                         "name":"collider",
                         "type":"bool",
                         "value":true
                        }]
                }, 
                {
                 "id":22,
                 "objectgroup":
                    {
                     "draworder":"index",
                     "id":2,
                     "name":"",
                     "objects":[
                            {
                             "height":256,
                             "id":2,
                             "name":"",
                             "rotation":0,
                             "type":"",
                             "visible":true,
                             "width":128,
                             "x":128,
                             "y":0
                            }],
                     "opacity":1,
                     "type":"objectgroup",
                     "visible":true,
                     "x":0,
                     "y":0
                    },
                 "properties":[
                        {
                         "name":"collider",
                         "type":"bool",
                         "value":true
                        }]
                }, 
                {
                 "id":23,
                 "objectgroup":
                    {
                     "draworder":"index",
                     "id":2,
                     "name":"",
                     "objects":[
                            {
                             "height":256,
                             "id":2,
                             "name":"",
                             "rotation":0,
                             "type":"",
                             "visible":true,
                             "width":128,
                             "x":0,
                             "y":0
                            }],
                     "opacity":1,
                     "type":"objectgroup",
                     "visible":true,
                     "x":0,
                     "y":0
                    },
                 "properties":[
                        {
                         "name":"collider",
                         "type":"bool",
                         "value":true
                        }]
                }, 
                {
                 "id":24,
                 "objectgroup":
                    {
                     "draworder":"index",
                     "id":2,
                     "name":"",
                     "objects":[
                            {
                             "height":117,
                             "id":1,
                             "name":"",
                             "rotation":0,
                             "type":"",
                             "visible":true,
                             "width":256,
                             "x":0,
                             "y":139
                            }],
                     "opacity":1,
                     "type":"objectgroup",
                     "visible":true,
                     "x":0,
                     "y":0
                    },
                 "properties":[
                        {
                         "name":"collider",
                         "type":"bool",
                         "value":true
                        }]
                }, 
                {
                 "id":25,
                 "objectgroup":
                    {
                     "draworder":"index",
                     "id":2,
                     "name":"",
                     "objects":[
                            {
                             "height":256,
                             "id":2,
                             "name":"",
                             "rotation":0,
                             "type":"",
                             "visible":true,
                             "width":128,
                             "x":128,
                             "y":0
                            }],
                     "opacity":1,
                     "type":"objectgroup",
                     "visible":true,
                     "x":0,
                     "y":0
                    },
                 "properties":[
                        {
                         "name":"collider",
                         "type":"bool",
                         "value":true
                        }]
                }, 
                {
                 "id":26,
                 "objectgroup":
                    {
                     "draworder":"index",
                     "id":2,
                     "name":"",
                     "objects":[
                            {
                             "height":256,
                             "id":2,
                             "name":"",
                             "rotation":0,
                             "type":"",
                             "visible":true,
                             "width":128,
                             "x":0,
                             "y":0
                            }],
                     "opacity":1,
                     "type":"objectgroup",
                     "visible":true,
                     "x":0,
                     "y":0
                    },
                 "properties":[
                        {
                         "name":"collider",
                         "type":"bool",
                         "value":true
                        }]
                }, 
                {
                 "id":27,
                 "objectgroup":
                    {
                     "draworder":"index",
                     "id":2,
                     "name":"",
                     "objects":[
                            {
                             "height":117,
                             "id":1,
                             "name":"",
                             "rotation":0,
                             "type":"",
                             "visible":true,
                             "width":256,
                             "x":0,
                             "y":139
                            }],
                     "opacity":1,
                     "type":"objectgroup",
                     "visible":true,
                     "x":0,
                     "y":0
                    },
                 "properties":[
                        {
                         "name":"collider",
                         "type":"bool",
                         "value":true
                        }]
                }, 
                {
                 "id":28,
                 "objectgroup":
                    {
                     "draworder":"index",
                     "id":2,
                     "name":"",
                     "objects":[
                            {
                             "height":256,
                             "id":2,
                             "name":"",
                             "rotation":0,
                             "type":"",
                             "visible":true,
                             "width":128,
                             "x":128,
                             "y":0
                            }],
                     "opacity":1,
                     "type":"objectgroup",
                     "visible":true,
                     "x":0,
                     "y":0
                    },
                 "properties":[
                        {
                         "name":"collider",
                         "type":"bool",
                         "value":true
                        }]
                }, 
                {
                 "id":30,
                 "objectgroup":
                    {
                     "draworder":"index",
                     "id":2,
                     "name":"",
                     "objects":[
                            {
                             "height":143,
                             "id":1,
                             "name":"",
                             "rotation":0,
                             "type":"",
                             "visible":true,
                             "width":256,
                             "x":0,
                             "y":0
                            }],
                     "opacity":1,
                     "type":"objectgroup",
                     "visible":true,
                     "x":0,
                     "y":0
                    },
                 "properties":[
                        {
                         "name":"collider",
                         "type":"bool",
                         "value":true
                        }]
                }, 
                {
                 "id":31,
                 "objectgroup":
                    {
                     "draworder":"index",
                     "id":2,
                     "name":"",
                     "objects":[
                            {
                             "height":143,
                             "id":1,
                             "name":"",
                             "rotation":0,
                             "type":"",
                             "visible":true,
                             "width":256,
                             "x":0,
                             "y":0
                            }],
                     "opacity":1,
                     "type":"objectgroup",
                     "visible":true,
                     "x":0,
                     "y":0
                    },
                 "properties":[
                        {
                         "name":"collider",
                         "type":"bool",
                         "value":true
                        }]
                }, 
                {
                 "id":32,
                 "objectgroup":
                    {
                     "draworder":"index",
                     "id":2,
                     "name":"",
                     "objects":[
                            {
                             "height":143,
                             "id":1,
                             "name":"",
                             "rotation":0,
                             "type":"",
                             "visible":true,
                             "width":256,
                             "x":0,
                             "y":0
                            }],
                     "opacity":1,
                     "type":"objectgroup",
                     "visible":true,
                     "x":0,
                     "y":0
                    },
                 "properties":[
                        {
                         "name":"collider",
                         "type":"bool",
                         "value":true
                        }]
                }, 
                {
                 "id":33,
                 "objectgroup":
                    {
                     "draworder":"index",
                     "id":2,
                     "name":"",
                     "objects":[
                            {
                             "height":143,
                             "id":1,
                             "name":"",
                             "rotation":0,
                             "type":"",
                             "visible":true,
                             "width":256,
                             "x":0,
                             "y":0
                            }],
                     "opacity":1,
                     "type":"objectgroup",
                     "visible":true,
                     "x":0,
                     "y":0
                    },
                 "properties":[
                        {
                         "name":"collider",
                         "type":"bool",
                         "value":true
                        }]
                }, 
                {
                 "id":34,
                 "objectgroup":
                    {
                     "draworder":"index",
                     "id":2,
                     "name":"",
                     "objects":[
                            {
                             "height":143,
                             "id":1,
                             "name":"",
                             "rotation":0,
                             "type":"",
                             "visible":true,
                             "width":256,
                             "x":0,
                             "y":0
                            }],
                     "opacity":1,
                     "type":"objectgroup",
                     "visible":true,
                     "x":0,
                     "y":0
                    },
                 "properties":[
                        {
                         "name":"collider",
                         "type":"bool",
                         "value":true
                        }]
                }, 
                {
                 "id":35,
                 "objectgroup":
                    {
                     "draworder":"index",
                     "id":2,
                     "name":"",
                     "objects":[
                            {
                             "height":143,
                             "id":1,
                             "name":"",
                             "rotation":0,
                             "type":"",
                             "visible":true,
                             "width":256,
                             "x":0,
                             "y":0
                            }],
                     "opacity":1,
                     "type":"objectgroup",
                     "visible":true,
                     "x":0,
                     "y":0
                    },
                 "properties":[
                        {
                         "name":"collider",
                         "type":"bool",
                         "value":true
                        }]
                }, 
                {
                 "id":36,
                 "objectgroup":
                    {
                     "draworder":"index",
                     "id":2,
                     "name":"",
                     "objects":[
                            {
                             "height":143,
                             "id":1,
                             "name":"",
                             "rotation":0,
                             "type":"",
                             "visible":true,
                             "width":256,
                             "x":0,
                             "y":0
                            }],
                     "opacity":1,
                     "type":"objectgroup",
                     "visible":true,
                     "x":0,
                     "y":0
                    },
                 "properties":[
                        {
                         "name":"collider",
                         "type":"bool",
                         "value":true
                        }]
                }, 
                {
                 "id":37,
                 "objectgroup":
                    {
                     "draworder":"index",
                     "id":2,
                     "name":"",
                     "objects":[
                            {
                             "height":143,
                             "id":1,
                             "name":"",
                             "rotation":0,
                             "type":"",
                             "visible":true,
                             "width":256,
                             "x":0,
                             "y":0
                            }],
                     "opacity":1,
                     "type":"objectgroup",
                     "visible":true,
                     "x":0,
                     "y":0
                    },
                 "properties":[
                        {
                         "name":"collider",
                         "type":"bool",
                         "value":true
                        }]
                }, 
                {
                 "id":38,
                 "objectgroup":
                    {
                     "draworder":"index",
                     "id":2,
                     "name":"",
                     "objects":[
                            {
                             "height":143,
                             "id":1,
                             "name":"",
                             "rotation":0,
                             "type":"",
                             "visible":true,
                             "width":256,
                             "x":0,
                             "y":0
                            }],
                     "opacity":1,
                     "type":"objectgroup",
                     "visible":true,
                     "x":0,
                     "y":0
                    },
                 "properties":[
                        {
                         "name":"collider",
                         "type":"bool",
                         "value":true
                        }]
                }, 
                {
                 "id":40,
                 "objectgroup":
                    {
                     "draworder":"index",
                     "id":2,
                     "name":"",
                     "objects":[
                            {
                             "height":143,
                             "id":1,
                             "name":"",
                             "rotation":0,
                             "type":"",
                             "visible":true,
                             "width":256,
                             "x":0,
                             "y":0
                            }],
                     "opacity":1,
                     "type":"objectgroup",
                     "visible":true,
                     "x":0,
                     "y":0
                    },
                 "properties":[
                        {
                         "name":"collider",
                         "type":"bool",
                         "value":true
                        }]
                }, 
                {
                 "id":41,
                 "objectgroup":
                    {
                     "draworder":"index",
                     "id":2,
                     "name":"",
                     "objects":[
                            {
                             "height":143,
                             "id":2,
                             "name":"",
                             "rotation":0,
                             "type":"",
                             "visible":true,
                             "width":256,
                             "x":0,
                             "y":0
                            }],
                     "opacity":1,
                     "type":"objectgroup",
                     "visible":true,
                     "x":0,
                     "y":0
                    },
                 "properties":[
                        {
                         "name":"collider",
                         "type":"bool",
                         "value":true
                        }]
                }, 
                {
                 "id":43,
                 "objectgroup":
                    {
                     "draworder":"index",
                     "id":2,
                     "name":"",
                     "objects":[
                            {
                             "height":143,
                             "id":1,
                             "name":"",
                             "rotation":0,
                             "type":"",
                             "visible":true,
                             "width":256,
                             "x":0,
                             "y":0
                            }],
                     "opacity":1,
                     "type":"objectgroup",
                     "visible":true,
                     "x":0,
                     "y":0
                    },
                 "properties":[
                        {
                         "name":"collider",
                         "type":"bool",
                         "value":true
                        }]
                }, 
                {
                 "id":44,
                 "objectgroup":
                    {
                     "draworder":"index",
                     "id":2,
                     "name":"",
                     "objects":[
                            {
                             "height":143,
                             "id":1,
                             "name":"",
                             "rotation":0,
                             "type":"",
                             "visible":true,
                             "width":256,
                             "x":0,
                             "y":0
                            }],
                     "opacity":1,
                     "type":"objectgroup",
                     "visible":true,
                     "x":0,
                     "y":0
                    },
                 "properties":[
                        {
                         "name":"collider",
                         "type":"bool",
                         "value":true
                        }]
                }, 
                {
                 "id":46,
                 "objectgroup":
                    {
                     "draworder":"index",
                     "id":2,
                     "name":"",
                     "objects":[
                            {
                             "height":143,
                             "id":1,
                             "name":"",
                             "rotation":0,
                             "type":"",
                             "visible":true,
                             "width":256,
                             "x":0,
                             "y":0
                            }],
                     "opacity":1,
                     "type":"objectgroup",
                     "visible":true,
                     "x":0,
                     "y":0
                    },
                 "properties":[
                        {
                         "name":"collider",
                         "type":"bool",
                         "value":true
                        }]
                }, 
                {
                 "id":47,
                 "objectgroup":
                    {
                     "draworder":"index",
                     "id":2,
                     "name":"",
                     "objects":[
                            {
                             "height":143,
                             "id":1,
                             "name":"",
                             "rotation":0,
                             "type":"",
                             "visible":true,
                             "width":256,
                             "x":0,
                             "y":0
                            }],
                     "opacity":1,
                     "type":"objectgroup",
                     "visible":true,
                     "x":0,
                     "y":0
                    },
                 "properties":[
                        {
                         "name":"collider",
                         "type":"bool",
                         "value":true
                        }]
                }, 
                {
                 "id":50,
                 "objectgroup":
                    {
                     "draworder":"index",
                     "id":2,
                     "name":"",
                     "objects":[
                            {
                             "height":143,
                             "id":1,
                             "name":"",
                             "rotation":0,
                             "type":"",
                             "visible":true,
                             "width":256,
                             "x":0,
                             "y":0
                            }],
                     "opacity":1,
                     "type":"objectgroup",
                     "visible":true,
                     "x":0,
                     "y":0
                    },
                 "properties":[
                        {
                         "name":"collider",
                         "type":"bool",
                         "value":true
                        }]
                }, 
                {
                 "id":51,
                 "objectgroup":
                    {
                     "draworder":"index",
                     "id":2,
                     "name":"",
                     "objects":[
                            {
                             "height":143,
                             "id":1,
                             "name":"",
                             "rotation":0,
                             "type":"",
                             "visible":true,
                             "width":256,
                             "x":0,
                             "y":0
                            }, 
                            {
                             "height":143,
                             "id":2,
                             "name":"",
                             "rotation":0,
                             "type":"",
                             "visible":true,
                             "width":256,
                             "x":0,
                             "y":0
                            }],
                     "opacity":1,
                     "type":"objectgroup",
                     "visible":true,
                     "x":0,
                     "y":0
                    },
                 "properties":[
                        {
                         "name":"collider",
                         "type":"bool",
                         "value":true
                        }]
                }, 
                {
                 "id":52,
                 "objectgroup":
                    {
                     "draworder":"index",
                     "id":2,
                     "name":"",
                     "objects":[
                            {
                             "height":143,
                             "id":1,
                             "name":"",
                             "rotation":0,
                             "type":"",
                             "visible":true,
                             "width":256,
                             "x":0,
                             "y":0
                            }],
                     "opacity":1,
                     "type":"objectgroup",
                     "visible":true,
                     "x":0,
                     "y":0
                    },
                 "properties":[
                        {
                         "name":"collider",
                         "type":"bool",
                         "value":true
                        }]
                }, 
                {
                 "id":53,
                 "properties":[
                        {
                         "name":"collider",
                         "type":"bool",
                         "value":true
                        }]
                }, 
                {
                 "id":54,
                 "objectgroup":
                    {
                     "draworder":"index",
                     "id":2,
                     "name":"",
                     "objects":[
                            {
                             "height":95.0822,
                             "id":1,
                             "name":"",
                             "rotation":0,
                             "type":"",
                             "visible":true,
                             "width":256,
                             "x":0,
                             "y":160.918
                            }],
                     "opacity":1,
                     "type":"objectgroup",
                     "visible":true,
                     "x":0,
                     "y":0
                    },
                 "properties":[
                        {
                         "name":"collider",
                         "type":"bool",
                         "value":true
                        }]
                }, 
                {
                 "id":56,
                 "objectgroup":
                    {
                     "draworder":"index",
                     "id":2,
                     "name":"",
                     "objects":[
                            {
                             "height":143,
                             "id":1,
                             "name":"",
                             "rotation":0,
                             "type":"",
                             "visible":true,
                             "width":256,
                             "x":0,
                             "y":0
                            }],
                     "opacity":1,
                     "type":"objectgroup",
                     "visible":true,
                     "x":0,
                     "y":0
                    },
                 "properties":[
                        {
                         "name":"collider",
                         "type":"bool",
                         "value":true
                        }]
                }, 
                {
                 "id":57,
                 "objectgroup":
                    {
                     "draworder":"index",
                     "id":2,
                     "name":"",
                     "objects":[
                            {
                             "height":143,
                             "id":1,
                             "name":"",
                             "rotation":0,
                             "type":"",
                             "visible":true,
                             "width":256,
                             "x":0,
                             "y":0
                            }],
                     "opacity":1,
                     "type":"objectgroup",
                     "visible":true,
                     "x":0,
                     "y":0
                    },
                 "properties":[
                        {
                         "name":"collider",
                         "type":"bool",
                         "value":true
                        }]
                }, 
                {
                 "id":58,
                 "objectgroup":
                    {
                     "draworder":"index",
                     "id":2,
                     "name":"",
                     "objects":[
                            {
                             "height":143,
                             "id":1,
                             "name":"",
                             "rotation":0,
                             "type":"",
                             "visible":true,
                             "width":256,
                             "x":0,
                             "y":0
                            }],
                     "opacity":1,
                     "type":"objectgroup",
                     "visible":true,
                     "x":0,
                     "y":0
                    },
                 "properties":[
                        {
                         "name":"collider",
                         "type":"bool",
                         "value":true
                        }]
                }, 
                {
                 "id":60,
                 "objectgroup":
                    {
                     "draworder":"index",
                     "id":2,
                     "name":"",
                     "objects":[
                            {
                             "height":143,
                             "id":1,
                             "name":"",
                             "rotation":0,
                             "type":"",
                             "visible":true,
                             "width":256,
                             "x":0,
                             "y":0
                            }],
                     "opacity":1,
                     "type":"objectgroup",
                     "visible":true,
                     "x":0,
                     "y":0
                    },
                 "properties":[
                        {
                         "name":"collider",
                         "type":"bool",
                         "value":true
                        }]
                }, 
                {
                 "id":61,
                 "objectgroup":
                    {
                     "draworder":"index",
                     "id":2,
                     "name":"",
                     "objects":[
                            {
                             "height":143,
                             "id":1,
                             "name":"",
                             "rotation":0,
                             "type":"",
                             "visible":true,
                             "width":256,
                             "x":0,
                             "y":0
                            }],
                     "opacity":1,
                     "type":"objectgroup",
                     "visible":true,
                     "x":0,
                     "y":0
                    },
                 "properties":[
                        {
                         "name":"collider",
                         "type":"bool",
                         "value":true
                        }]
                }, 
                {
                 "id":63,
                 "objectgroup":
                    {
                     "draworder":"index",
                     "id":2,
                     "name":"",
                     "objects":[
                            {
                             "height":256,
                             "id":1,
                             "name":"",
                             "rotation":0,
                             "type":"",
                             "visible":true,
                             "width":256,
                             "x":0,
                             "y":0
                            }],
                     "opacity":1,
                     "type":"objectgroup",
                     "visible":true,
                     "x":0,
                     "y":0
                    },
                 "properties":[
                        {
                         "name":"collider",
                         "type":"bool",
                         "value":true
                        }]
                }, 
                {
                 "id":66,
                 "objectgroup":
                    {
                     "draworder":"index",
                     "id":2,
                     "name":"",
                     "objects":[
                            {
                             "height":143,
                             "id":1,
                             "name":"",
                             "rotation":0,
                             "type":"",
                             "visible":true,
                             "width":256,
                             "x":0,
                             "y":0
                            }],
                     "opacity":1,
                     "type":"objectgroup",
                     "visible":true,
                     "x":0,
                     "y":0
                    },
                 "properties":[
                        {
                         "name":"collider",
                         "type":"bool",
                         "value":true
                        }]
                }, 
                {
                 "id":67,
                 "objectgroup":
                    {
                     "draworder":"index",
                     "id":2,
                     "name":"",
                     "objects":[
                            {
                             "height":143,
                             "id":1,
                             "name":"",
                             "rotation":0,
                             "type":"",
                             "visible":true,
                             "width":256,
                             "x":0,
                             "y":0
                            }],
                     "opacity":1,
                     "type":"objectgroup",
                     "visible":true,
                     "x":0,
                     "y":0
                    },
                 "properties":[
                        {
                         "name":"collider",
                         "type":"bool",
                         "value":true
                        }]
                }, 
                {
                 "id":70,
                 "objectgroup":
                    {
                     "draworder":"index",
                     "id":2,
                     "name":"",
                     "objects":[
                            {
                             "height":95,
                             "id":1,
                             "name":"",
                             "rotation":0,
                             "type":"",
                             "visible":true,
                             "width":256,
                             "x":0,
                             "y":0
                            }],
                     "opacity":1,
                     "type":"objectgroup",
                     "visible":true,
                     "x":0,
                     "y":0
                    },
                 "properties":[
                        {
                         "name":"collider",
                         "type":"bool",
                         "value":true
                        }]
                }, 
                {
                 "id":71,
                 "objectgroup":
                    {
                     "draworder":"index",
                     "id":2,
                     "name":"",
                     "objects":[
                            {
                             "height":95.7671,
                             "id":1,
                             "name":"",
                             "rotation":0,
                             "type":"",
                             "visible":true,
                             "width":256,
                             "x":0,
                             "y":160.233
                            }],
                     "opacity":1,
                     "type":"objectgroup",
                     "visible":true,
                     "x":0,
                     "y":0
                    },
                 "properties":[
                        {
                         "name":"collider",
                         "type":"bool",
                         "value":true
                        }]
                }, 
                {
                 "id":76,
                 "objectgroup":
                    {
                     "draworder":"index",
                     "id":2,
                     "name":"",
                     "objects":[
                            {
                             "height":95,
                             "id":1,
                             "name":"",
                             "rotation":0,
                             "type":"",
                             "visible":true,
                             "width":256,
                             "x":0,
                             "y":0
                            }],
                     "opacity":1,
                     "type":"objectgroup",
                     "visible":true,
                     "x":0,
                     "y":0
                    },
                 "properties":[
                        {
                         "name":"collider",
                         "type":"bool",
                         "value":true
                        }]
                }, 
                {
                 "id":77,
                 "objectgroup":
                    {
                     "draworder":"index",
                     "id":2,
                     "name":"",
                     "objects":[
                            {
                             "height":95.7671,
                             "id":1,
                             "name":"",
                             "rotation":0,
                             "type":"",
                             "visible":true,
                             "width":256,
                             "x":0,
                             "y":160.233
                            }],
                     "opacity":1,
                     "type":"objectgroup",
                     "visible":true,
                     "x":0,
                     "y":0
                    },
                 "properties":[
                        {
                         "name":"collider",
                         "type":"bool",
                         "value":true
                        }]
                }, 
                {
                 "id":80,
                 "objectgroup":
                    {
                     "draworder":"index",
                     "id":2,
                     "name":"",
                     "objects":[
                            {
                             "height":256,
                             "id":1,
                             "name":"",
                             "rotation":0,
                             "type":"",
                             "visible":true,
                             "width":256,
                             "x":0,
                             "y":0
                            }],
                     "opacity":1,
                     "type":"objectgroup",
                     "visible":true,
                     "x":0,
                     "y":0
                    },
                 "properties":[
                        {
                         "name":"collider",
                         "type":"bool",
                         "value":true
                        }]
                }, 
                {
                 "id":81,
                 "objectgroup":
                    {
                     "draworder":"index",
                     "id":2,
                     "name":"",
                     "objects":[
                            {
                             "height":62.9863,
                             "id":1,
                             "name":"",
                             "rotation":0,
                             "type":"",
                             "visible":true,
                             "width":224,
                             "x":16,
                             "y":193.014
                            }],
                     "opacity":1,
                     "type":"objectgroup",
                     "visible":true,
                     "x":0,
                     "y":0
                    },
                 "properties":[
                        {
                         "name":"collider",
                         "type":"bool",
                         "value":true
                        }]
                }, 
                {
                 "id":82,
                 "objectgroup":
                    {
                     "draworder":"index",
                     "id":2,
                     "name":"",
                     "objects":[
                            {
                             "height":60,
                             "id":1,
                             "name":"",
                             "rotation":0,
                             "type":"",
                             "visible":true,
                             "width":224,
                             "x":16,
                             "y":0
                            }],
                     "opacity":1,
                     "type":"objectgroup",
                     "visible":true,
                     "x":0,
                     "y":0
                    },
                 "properties":[
                        {
                         "name":"collider",
                         "type":"bool",
                         "value":true
                        }]
                }, 
                {
                 "id":86,
                 "objectgroup":
                    {
                     "draworder":"index",
                     "id":2,
                     "name":"",
                     "objects":[
                            {
                             "height":256,
                             "id":1,
                             "name":"",
                             "rotation":0,
                             "type":"",
                             "visible":true,
                             "width":256,
                             "x":0,
                             "y":0
                            }],
                     "opacity":1,
                     "type":"objectgroup",
                     "visible":true,
                     "x":0,
                     "y":0
                    },
                 "properties":[
                        {
                         "name":"collider",
                         "type":"bool",
                         "value":true
                        }]
                }, 
                {
                 "id":87,
                 "properties":[
                        {
                         "name":"collider",
                         "type":"bool",
                         "value":false
                        }]
                }, 
                {
                 "id":90,
                 "properties":[
                        {
                         "name":"collider",
                         "type":"bool",
                         "value":false
                        }]
                }, 
                {
                 "id":91,
                 "properties":[
                        {
                         "name":"collider",
                         "type":"bool",
                         "value":false
                        }]
                }, 
                {
                 "id":92,
                 "properties":[
                        {
                         "name":"collider",
                         "type":"bool",
                         "value":false
                        }]
                }, 
                {
                 "id":93,
                 "properties":[
                        {
                         "name":"collider",
                         "type":"bool",
                         "value":false
                        }]
                }, 
                {
                 "id":94,
                 "objectgroup":
                    {
                     "draworder":"index",
                     "id":2,
                     "name":"",
                     "objects":[
                            {
                             "height":256,
                             "id":1,
                             "name":"",
                             "rotation":0,
                             "type":"",
                             "visible":true,
                             "width":256,
                             "x":0,
                             "y":0
                            }],
                     "opacity":1,
                     "type":"objectgroup",
                     "visible":true,
                     "x":0,
                     "y":0
                    },
                 "properties":[
                        {
                         "name":"collider",
                         "type":"bool",
                         "value":true
                        }]
                }, 
                {
                 "id":95,
                 "properties":[
                        {
                         "name":"collider",
                         "type":"bool",
                         "value":false
                        }]
                }, 
                {
                 "id":96,
                 "properties":[
                        {
                         "name":"collider",
                         "type":"bool",
                         "value":false
                        }]
                }, 
                {
                 "id":97,
                 "properties":[
                        {
                         "name":"collider",
                         "type":"bool",
                         "value":false
                        }]
                }],
         "tilewidth":256
        }],
 "tilewidth":256,
 "type":"map",
 "version":"1.6",
 "width":16
}